quantlet/__init__.py
quantlet/_version.py
quantlet/agents/__init__.py
quantlet/agents/agent.py
quantlet/agents/concurrent.py
quantlet/agents/simulation.py
quantlet/ml.py
quantlet/reactives.py
quantlet/strats/__init__.py
quantlet/strats/bands.py
quantlet/strats/filter.py
quantlet/strats/mathfin.py
quantlet/strats/plot.py
quantlet/strats/rw.py
quantlet/streaming/__init__.py
quantlet/streaming/dataframe.py
quantlet/streaming/iterables.py
quantlet/streaming/metadata.py
quantlet/streaming/stream.py
quantlet/timeseries/__init__.py
quantlet/timeseries/alpaca.py
quantlet/timeseries/common.py
quantlet/timeseries/datasets.py
quantlet/utils/__init__.py
quantlet/utils/graph.py
quantlet-1.0.0.dist-info/LICENSE.txt
quantlet-1.0.0.dist-info/WHEEL
quantlet-1.0.0.dist-info/METADATA
quantlet-1.0.0.dist-info/RECORD
