Metadata-Version: 2.1
Name: quantlet
Version: 1.0.0
Summary: QuantLET - an event driven framework for large scale real-time analytics
Home-page: https://gitlab.com/quantlet/quantlet
License: AGPL-3.0-or-later
Author: J Faleiro
Author-email: j@falei.ro
Requires-Python: >=3.8,<4.0
Classifier: Development Status :: 4 - Beta
Classifier: Intended Audience :: Developers
Classifier: License :: OSI Approved :: GNU Affero General Public License v3
Classifier: License :: OSI Approved :: GNU Affero General Public License v3 or later (AGPLv3+)
Classifier: Operating System :: OS Independent
Classifier: Programming Language :: Python
Classifier: Programming Language :: Python :: 3
Classifier: Programming Language :: Python :: 3.8
Classifier: Programming Language :: Python :: 3.9
Classifier: Topic :: Software Development
Classifier: Topic :: Software Development :: Libraries :: Python Modules
Provides-Extra: agents
Provides-Extra: coverage
Provides-Extra: dl
Provides-Extra: interactive-dev
Provides-Extra: ml
Provides-Extra: reactives
Provides-Extra: strats
Provides-Extra: streaming
Provides-Extra: tests
Provides-Extra: timeseries
Requires-Dist: PyHamcrest; extra == "tests" or extra == "coverage"
Requires-Dist: autopep8 (>=1.5.5,<2.0.0); extra == "interactive-dev"
Requires-Dist: coverage (>=5.4,<6.0); extra == "coverage"
Requires-Dist: flake8 (>=3.8.4,<4.0.0); extra == "interactive-dev"
Requires-Dist: isort (>=5.7.0,<6.0.0); extra == "interactive-dev"
Requires-Dist: pre-commit (>=2.10.1,<3.0.0); extra == "interactive-dev"
Requires-Dist: pylint (>=2.7.0,<3.0.0)
Requires-Dist: pytest (>=6.2.2,<7.0.0); extra == "tests" or extra == "coverage"
Requires-Dist: quantlet.agents (>=0.0.1,<0.0.2); extra == "agents"
Requires-Dist: quantlet.core (>=0.0.3,<0.0.4)
Requires-Dist: quantlet.ml (>=0.0.3,<0.0.4); extra == "ml"
Requires-Dist: quantlet.reactives (>=0.0.2,<0.0.3); extra == "reactives"
Requires-Dist: quantlet.strats (>=0.0.2,<0.0.3); extra == "strats"
Requires-Dist: quantlet.streaming (>=1.0.0,<2.0.0); extra == "streaming"
Requires-Dist: quantlet.timeseries (>=0.0.2,<0.0.3); extra == "timeseries"
Requires-Dist: rope (>=0.18.0,<0.19.0); extra == "interactive-dev"
